ethicalai/__init__py
ethicalai/dataset.py
ethicalai/study.py
ethicalai/utils.py
ethicalai-0.0.0.dist-info/LICENSE
ethicalai-0.0.0.dist-info/WHEEL
ethicalai-0.0.0.dist-info/METADATA
ethicalai-0.0.0.dist-info/RECORD
